<?xml version="1.0" encoding="UTF-8"?>
<comments>
	<comment words="27" words_in_dictionary="0.40741" ngram_probability="0.28469" percentage_of_trasnlit_rules="0.00000" cumulative_probability="0.00000">
		<original>Tieši to pašu , ka valdības darbs ir jāizvērtē , vakar teica R. Dzintars. NA uz raidijumu 100. pants vajadzētu sūtīt kompetentākus pārstāvjus, piemēram J. Dombravu, spējīgākus komptenti izskaidrot partijas nostāju.</original>
		<words>
			<word is_in_dictionary="0" ngram_probability="0.00000" percentage_of_trasnlit_rules="0.00000">Tieši</word>
			<word is_in_dictionary="1" ngram_probability="0.48654" percentage_of_trasnlit_rules="0.00000">to</word>
			<word is_in_dictionary="0" ngram_probability="0.00000" percentage_of_trasnlit_rules="0.00000">pašu</word>
			<word is_in_dictionary="1" ngram_probability="0.50228" percentage_of_trasnlit_rules="0.00000">ka</word>
			<word is_in_dictionary="0" ngram_probability="0.00000" percentage_of_trasnlit_rules="0.00000">valdības</word>
			<word is_in_dictionary="1" ngram_probability="0.48212" percentage_of_trasnlit_rules="0.00000">darbs</word>
			<word is_in_dictionary="1" ngram_probability="0.48475" percentage_of_trasnlit_rules="0.00000">ir</word>
			<word is_in_dictionary="0" ngram_probability="0.00000" percentage_of_trasnlit_rules="0.00000">jāizvērtē</word>
			<word is_in_dictionary="0" ngram_probability="0.49558" percentage_of_trasnlit_rules="0.00000">vakar</word>
			<word is_in_dictionary="1" ngram_probability="0.52370" percentage_of_trasnlit_rules="0.00000">teica</word>
			<word is_in_dictionary="1" ngram_probability="0.49690" percentage_of_trasnlit_rules="0.00000">Dzintars</word>
			<word is_in_dictionary="0" ngram_probability="0.49783" percentage_of_trasnlit_rules="0.00000">NA</word>
			<word is_in_dictionary="1" ngram_probability="0.47952" percentage_of_trasnlit_rules="0.00000">uz</word>
			<word is_in_dictionary="0" ngram_probability="0.50227" percentage_of_trasnlit_rules="0.00000">raidijumu</word>
			<word is_in_dictionary="0" ngram_probability="0.32367" percentage_of_trasnlit_rules="0.00000">100</word>
			<word is_in_dictionary="1" ngram_probability="0.49214" percentage_of_trasnlit_rules="0.00000">pants</word>
			<word is_in_dictionary="0" ngram_probability="0.00000" percentage_of_trasnlit_rules="0.00000">vajadzētu</word>
			<word is_in_dictionary="0" ngram_probability="0.00000" percentage_of_trasnlit_rules="0.00000">sūtīt</word>
			<word is_in_dictionary="0" ngram_probability="0.00000" percentage_of_trasnlit_rules="0.00000">kompetentākus</word>
			<word is_in_dictionary="0" ngram_probability="0.00000" percentage_of_trasnlit_rules="0.00000">pārstāvjus</word>
			<word is_in_dictionary="0" ngram_probability="0.00000" percentage_of_trasnlit_rules="0.00000">piemēram</word>
			<word is_in_dictionary="1" ngram_probability="0.44252" percentage_of_trasnlit_rules="0.00000">Dombravu</word>
			<word is_in_dictionary="0" ngram_probability="0.00000" percentage_of_trasnlit_rules="0.00000">spējīgākus</word>
			<word is_in_dictionary="1" ngram_probability="0.48829" percentage_of_trasnlit_rules="0.00000">komptenti</word>
			<word is_in_dictionary="0" ngram_probability="0.48434" percentage_of_trasnlit_rules="0.00000">izskaidrot</word>
			<word is_in_dictionary="1" ngram_probability="0.50417" percentage_of_trasnlit_rules="0.00000">partijas</word>
			<word is_in_dictionary="0" ngram_probability="0.00000" percentage_of_trasnlit_rules="0.00000">nostāju</word>
		</words>
	</comment>
	<comment words="75" words_in_dictionary="0.57333" ngram_probability="0.31613" percentage_of_trasnlit_rules="0.00000" cumulative_probability="0.00000">
		<original>Nu to tu paprasi Zatlerim, ko viņš ar to domājis, un kā viņš tehniski to grib izdarīt, es viņu slavēju par R2 un RP izveidošanu, kas ļāva atbrīvoties no diviem A, trešais arī nedaudz noplaka, un, par to, ka oligarhu ielikts, viņš, tomēr, tiem nekalpoja, bet, es esmu tālu no tā, lai atzītu par nekļūdīgu pilnīgi visu, ko viņš dara vai saka, tā ka par šo priekšlikumu varu pateikt to pašu, ko par analoģisku NA priekšlikumu.</original>
		<words>
			<word is_in_dictionary="1" ngram_probability="0.49563" percentage_of_trasnlit_rules="0.00000">Nu</word>
			<word is_in_dictionary="1" ngram_probability="0.48877" percentage_of_trasnlit_rules="0.00000">to</word>
			<word is_in_dictionary="0" ngram_probability="0.51288" percentage_of_trasnlit_rules="0.00000">tu</word>
			<word is_in_dictionary="1" ngram_probability="0.49821" percentage_of_trasnlit_rules="0.00000">paprasi</word>
			<word is_in_dictionary="1" ngram_probability="0.48462" percentage_of_trasnlit_rules="0.00000">Zatlerim</word>
			<word is_in_dictionary="1" ngram_probability="0.48830" percentage_of_trasnlit_rules="0.00000">ko</word>
			<word is_in_dictionary="0" ngram_probability="0.00000" percentage_of_trasnlit_rules="0.00000">viņš</word>
			<word is_in_dictionary="1" ngram_probability="0.51676" percentage_of_trasnlit_rules="0.00000">ar</word>
			<word is_in_dictionary="1" ngram_probability="0.48654" percentage_of_trasnlit_rules="0.00000">to</word>
			<word is_in_dictionary="0" ngram_probability="0.00000" percentage_of_trasnlit_rules="0.00000">domājis</word>
			<word is_in_dictionary="1" ngram_probability="0.49961" percentage_of_trasnlit_rules="0.00000">un</word>
			<word is_in_dictionary="0" ngram_probability="0.00000" percentage_of_trasnlit_rules="0.00000">kā</word>
			<word is_in_dictionary="0" ngram_probability="0.00000" percentage_of_trasnlit_rules="0.00000">viņš</word>
			<word is_in_dictionary="1" ngram_probability="0.45666" percentage_of_trasnlit_rules="0.00000">tehniski</word>
			<word is_in_dictionary="1" ngram_probability="0.49203" percentage_of_trasnlit_rules="0.00000">to</word>
			<word is_in_dictionary="0" ngram_probability="0.51502" percentage_of_trasnlit_rules="0.00000">grib</word>
			<word is_in_dictionary="0" ngram_probability="0.00000" percentage_of_trasnlit_rules="0.00000">izdarīt</word>
			<word is_in_dictionary="1" ngram_probability="0.49864" percentage_of_trasnlit_rules="0.00000">es</word>
			<word is_in_dictionary="0" ngram_probability="0.00000" percentage_of_trasnlit_rules="0.00000">viņu</word>
			<word is_in_dictionary="0" ngram_probability="0.00000" percentage_of_trasnlit_rules="0.00000">slavēju</word>
			<word is_in_dictionary="1" ngram_probability="0.48351" percentage_of_trasnlit_rules="0.00000">par</word>
			<word is_in_dictionary="0" ngram_probability="0.40975" percentage_of_trasnlit_rules="0.00000">R2</word>
			<word is_in_dictionary="1" ngram_probability="0.46452" percentage_of_trasnlit_rules="0.00000">un</word>
			<word is_in_dictionary="0" ngram_probability="0.50521" percentage_of_trasnlit_rules="0.00000">RP</word>
			<word is_in_dictionary="0" ngram_probability="0.00000" percentage_of_trasnlit_rules="0.00000">izveidošanu</word>
			<word is_in_dictionary="1" ngram_probability="0.49297" percentage_of_trasnlit_rules="0.00000">kas</word>
			<word is_in_dictionary="0" ngram_probability="0.00000" percentage_of_trasnlit_rules="0.00000">ļāva</word>
			<word is_in_dictionary="0" ngram_probability="0.00000" percentage_of_trasnlit_rules="0.00000">atbrīvoties</word>
			<word is_in_dictionary="1" ngram_probability="0.48862" percentage_of_trasnlit_rules="0.00000">no</word>
			<word is_in_dictionary="1" ngram_probability="0.48995" percentage_of_trasnlit_rules="0.00000">diviem</word>
			<word is_in_dictionary="0" ngram_probability="0.00000" percentage_of_trasnlit_rules="0.00000">trešais</word>
			<word is_in_dictionary="0" ngram_probability="0.00000" percentage_of_trasnlit_rules="0.00000">arī</word>
			<word is_in_dictionary="1" ngram_probability="0.48283" percentage_of_trasnlit_rules="0.00000">nedaudz</word>
			<word is_in_dictionary="1" ngram_probability="0.51149" percentage_of_trasnlit_rules="0.00000">noplaka</word>
			<word is_in_dictionary="1" ngram_probability="0.43510" percentage_of_trasnlit_rules="0.00000">un</word>
			<word is_in_dictionary="1" ngram_probability="0.49978" percentage_of_trasnlit_rules="0.00000">par</word>
			<word is_in_dictionary="1" ngram_probability="0.50748" percentage_of_trasnlit_rules="0.00000">to</word>
			<word is_in_dictionary="1" ngram_probability="0.50040" percentage_of_trasnlit_rules="0.00000">ka</word>
			<word is_in_dictionary="1" ngram_probability="0.46336" percentage_of_trasnlit_rules="0.00000">oligarhu</word>
			<word is_in_dictionary="1" ngram_probability="0.48346" percentage_of_trasnlit_rules="0.00000">ielikts</word>
			<word is_in_dictionary="0" ngram_probability="0.00000" percentage_of_trasnlit_rules="0.00000">viņš</word>
			<word is_in_dictionary="0" ngram_probability="0.00000" percentage_of_trasnlit_rules="0.00000">tomēr</word>
			<word is_in_dictionary="1" ngram_probability="0.49406" percentage_of_trasnlit_rules="0.00000">tiem</word>
			<word is_in_dictionary="1" ngram_probability="0.49082" percentage_of_trasnlit_rules="0.00000">nekalpoja</word>
			<word is_in_dictionary="1" ngram_probability="0.48480" percentage_of_trasnlit_rules="0.00000">bet</word>
			<word is_in_dictionary="1" ngram_probability="0.50560" percentage_of_trasnlit_rules="0.00000">es</word>
			<word is_in_dictionary="1" ngram_probability="0.27706" percentage_of_trasnlit_rules="0.00000">esmu</word>
			<word is_in_dictionary="0" ngram_probability="0.00000" percentage_of_trasnlit_rules="0.00000">tālu</word>
			<word is_in_dictionary="1" ngram_probability="0.48107" percentage_of_trasnlit_rules="0.00000">no</word>
			<word is_in_dictionary="0" ngram_probability="0.00000" percentage_of_trasnlit_rules="0.00000">tā</word>
			<word is_in_dictionary="1" ngram_probability="0.48836" percentage_of_trasnlit_rules="0.00000">lai</word>
			<word is_in_dictionary="0" ngram_probability="0.00000" percentage_of_trasnlit_rules="0.00000">atzītu</word>
			<word is_in_dictionary="1" ngram_probability="0.49278" percentage_of_trasnlit_rules="0.00000">par</word>
			<word is_in_dictionary="0" ngram_probability="0.00000" percentage_of_trasnlit_rules="0.00000">nekļūdīgu</word>
			<word is_in_dictionary="0" ngram_probability="0.00000" percentage_of_trasnlit_rules="0.00000">pilnīgi</word>
			<word is_in_dictionary="1" ngram_probability="0.47605" percentage_of_trasnlit_rules="0.00000">visu</word>
			<word is_in_dictionary="1" ngram_probability="0.48830" percentage_of_trasnlit_rules="0.00000">ko</word>
			<word is_in_dictionary="0" ngram_probability="0.00000" percentage_of_trasnlit_rules="0.00000">viņš</word>
			<word is_in_dictionary="1" ngram_probability="0.49373" percentage_of_trasnlit_rules="0.00000">dara</word>
			<word is_in_dictionary="0" ngram_probability="0.47744" percentage_of_trasnlit_rules="0.00000">vai</word>
			<word is_in_dictionary="1" ngram_probability="0.49841" percentage_of_trasnlit_rules="0.00000">saka</word>
			<word is_in_dictionary="0" ngram_probability="0.00000" percentage_of_trasnlit_rules="0.00000">tā</word>
			<word is_in_dictionary="1" ngram_probability="0.50228" percentage_of_trasnlit_rules="0.00000">ka</word>
			<word is_in_dictionary="1" ngram_probability="0.48351" percentage_of_trasnlit_rules="0.00000">par</word>
			<word is_in_dictionary="0" ngram_probability="0.00000" percentage_of_trasnlit_rules="0.00000">šo</word>
			<word is_in_dictionary="0" ngram_probability="0.00000" percentage_of_trasnlit_rules="0.00000">priekšlikumu</word>
			<word is_in_dictionary="1" ngram_probability="0.49004" percentage_of_trasnlit_rules="0.00000">varu</word>
			<word is_in_dictionary="1" ngram_probability="0.47439" percentage_of_trasnlit_rules="0.00000">pateikt</word>
			<word is_in_dictionary="1" ngram_probability="0.48945" percentage_of_trasnlit_rules="0.00000">to</word>
			<word is_in_dictionary="0" ngram_probability="0.00000" percentage_of_trasnlit_rules="0.00000">pašu</word>
			<word is_in_dictionary="1" ngram_probability="0.48830" percentage_of_trasnlit_rules="0.00000">ko</word>
			<word is_in_dictionary="1" ngram_probability="0.48351" percentage_of_trasnlit_rules="0.00000">par</word>
			<word is_in_dictionary="0" ngram_probability="0.00000" percentage_of_trasnlit_rules="0.00000">analoģisku</word>
			<word is_in_dictionary="0" ngram_probability="0.49783" percentage_of_trasnlit_rules="0.00000">NA</word>
			<word is_in_dictionary="0" ngram_probability="0.00000" percentage_of_trasnlit_rules="0.00000">priekšlikumu</word>
		</words>
	</comment>
	<comment words="84" words_in_dictionary="0.47619" ngram_probability="0.30382" percentage_of_trasnlit_rules="0.00000" cumulative_probability="0.00000">
		<original>Nebūs visumā sakarīga, liberāla, un rietumnieciska RP, būs daudz vairāk ZZS un vēl kas līdzīgs PLL, nedomā, ka viss RP elektorāts ies un nobalsos par V un NA, tad tik pieredzēsi to pašu, kas bija iepr. Saimā - ZZS un SC faktisko koalīciju un kopīgos balsojumus, vāja gan te daudziem tā atmiņa, pareizāk sakot "emocionāla" atmiņa, atceramis to, kas atbilst tai ainai, kas pašam galvā. Kaut, gaumes jau dažādas, "liberālis" jau te daudziem lamu vārds, īpaši tiem, kam vispār nav nekāda saprašana, ko tas vārds nozīmē.</original>
		<words>
			<word is_in_dictionary="0" ngram_probability="0.00000" percentage_of_trasnlit_rules="0.00000">Nebūs</word>
			<word is_in_dictionary="0" ngram_probability="0.00000" percentage_of_trasnlit_rules="0.00000">visumā</word>
			<word is_in_dictionary="0" ngram_probability="0.00000" percentage_of_trasnlit_rules="0.00000">sakarīga</word>
			<word is_in_dictionary="0" ngram_probability="0.00000" percentage_of_trasnlit_rules="0.00000">liberāla</word>
			<word is_in_dictionary="1" ngram_probability="0.49956" percentage_of_trasnlit_rules="0.00000">un</word>
			<word is_in_dictionary="0" ngram_probability="0.48991" percentage_of_trasnlit_rules="0.00000">rietumnieciska</word>
			<word is_in_dictionary="0" ngram_probability="0.49886" percentage_of_trasnlit_rules="0.00000">RP</word>
			<word is_in_dictionary="0" ngram_probability="0.00000" percentage_of_trasnlit_rules="0.00000">būs</word>
			<word is_in_dictionary="1" ngram_probability="0.48365" percentage_of_trasnlit_rules="0.00000">daudz</word>
			<word is_in_dictionary="0" ngram_probability="0.00000" percentage_of_trasnlit_rules="0.00000">vairāk</word>
			<word is_in_dictionary="1" ngram_probability="0.49783" percentage_of_trasnlit_rules="0.00000">ZZS</word>
			<word is_in_dictionary="1" ngram_probability="0.50673" percentage_of_trasnlit_rules="0.00000">un</word>
			<word is_in_dictionary="0" ngram_probability="0.00000" percentage_of_trasnlit_rules="0.00000">vēl</word>
			<word is_in_dictionary="1" ngram_probability="0.50565" percentage_of_trasnlit_rules="0.00000">kas</word>
			<word is_in_dictionary="0" ngram_probability="0.00000" percentage_of_trasnlit_rules="0.00000">līdzīgs</word>
			<word is_in_dictionary="0" ngram_probability="0.49783" percentage_of_trasnlit_rules="0.00000">PLL</word>
			<word is_in_dictionary="0" ngram_probability="0.00000" percentage_of_trasnlit_rules="0.00000">nedomā</word>
			<word is_in_dictionary="1" ngram_probability="0.49307" percentage_of_trasnlit_rules="0.00000">ka</word>
			<word is_in_dictionary="1" ngram_probability="0.47540" percentage_of_trasnlit_rules="0.00000">viss</word>
			<word is_in_dictionary="0" ngram_probability="0.50101" percentage_of_trasnlit_rules="0.00000">RP</word>
			<word is_in_dictionary="0" ngram_probability="0.00000" percentage_of_trasnlit_rules="0.00000">elektorāts</word>
			<word is_in_dictionary="0" ngram_probability="0.48549" percentage_of_trasnlit_rules="0.00000">ies</word>
			<word is_in_dictionary="1" ngram_probability="0.47196" percentage_of_trasnlit_rules="0.00000">un</word>
			<word is_in_dictionary="0" ngram_probability="0.48775" percentage_of_trasnlit_rules="0.00000">nobalsos</word>
			<word is_in_dictionary="1" ngram_probability="0.48351" percentage_of_trasnlit_rules="0.00000">par</word>
			<word is_in_dictionary="1" ngram_probability="0.49263" percentage_of_trasnlit_rules="0.00000">un</word>
			<word is_in_dictionary="0" ngram_probability="0.49077" percentage_of_trasnlit_rules="0.00000">NA</word>
			<word is_in_dictionary="1" ngram_probability="0.49683" percentage_of_trasnlit_rules="0.00000">tad</word>
			<word is_in_dictionary="0" ngram_probability="0.49603" percentage_of_trasnlit_rules="0.00000">tik</word>
			<word is_in_dictionary="0" ngram_probability="0.00000" percentage_of_trasnlit_rules="0.00000">pieredzēsi</word>
			<word is_in_dictionary="1" ngram_probability="0.48702" percentage_of_trasnlit_rules="0.00000">to</word>
			<word is_in_dictionary="0" ngram_probability="0.00000" percentage_of_trasnlit_rules="0.00000">pašu</word>
			<word is_in_dictionary="1" ngram_probability="0.55170" percentage_of_trasnlit_rules="0.00000">kas</word>
			<word is_in_dictionary="1" ngram_probability="0.48861" percentage_of_trasnlit_rules="0.00000">bija</word>
			<word is_in_dictionary="0" ngram_probability="0.48890" percentage_of_trasnlit_rules="0.00000">iepr</word>
			<word is_in_dictionary="0" ngram_probability="0.00000" percentage_of_trasnlit_rules="0.00000">Saimā</word>
			<word is_in_dictionary="1" ngram_probability="0.49783" percentage_of_trasnlit_rules="0.00000">ZZS</word>
			<word is_in_dictionary="1" ngram_probability="0.48375" percentage_of_trasnlit_rules="0.00000">un</word>
			<word is_in_dictionary="1" ngram_probability="0.49783" percentage_of_trasnlit_rules="0.00000">SC</word>
			<word is_in_dictionary="1" ngram_probability="0.47616" percentage_of_trasnlit_rules="0.00000">faktisko</word>
			<word is_in_dictionary="0" ngram_probability="0.00000" percentage_of_trasnlit_rules="0.00000">koalīciju</word>
			<word is_in_dictionary="1" ngram_probability="0.43510" percentage_of_trasnlit_rules="0.00000">un</word>
			<word is_in_dictionary="0" ngram_probability="0.00000" percentage_of_trasnlit_rules="0.00000">kopīgos</word>
			<word is_in_dictionary="1" ngram_probability="0.48275" percentage_of_trasnlit_rules="0.00000">balsojumus</word>
			<word is_in_dictionary="0" ngram_probability="0.00000" percentage_of_trasnlit_rules="0.00000">vāja</word>
			<word is_in_dictionary="1" ngram_probability="0.48307" percentage_of_trasnlit_rules="0.00000">gan</word>
			<word is_in_dictionary="0" ngram_probability="0.50529" percentage_of_trasnlit_rules="0.00000">te</word>
			<word is_in_dictionary="1" ngram_probability="0.48532" percentage_of_trasnlit_rules="0.00000">daudziem</word>
			<word is_in_dictionary="0" ngram_probability="0.00000" percentage_of_trasnlit_rules="0.00000">tā</word>
			<word is_in_dictionary="0" ngram_probability="0.00000" percentage_of_trasnlit_rules="0.00000">atmiņa</word>
			<word is_in_dictionary="0" ngram_probability="0.00000" percentage_of_trasnlit_rules="0.00000">pareizāk</word>
			<word is_in_dictionary="1" ngram_probability="0.50028" percentage_of_trasnlit_rules="0.00000">sakot</word>
			<word is_in_dictionary="0" ngram_probability="0.00000" percentage_of_trasnlit_rules="0.00000">emocionāla</word>
			<word is_in_dictionary="0" ngram_probability="0.00000" percentage_of_trasnlit_rules="0.00000">atmiņa</word>
			<word is_in_dictionary="0" ngram_probability="0.48877" percentage_of_trasnlit_rules="0.00000">atceramis</word>
			<word is_in_dictionary="1" ngram_probability="0.49718" percentage_of_trasnlit_rules="0.00000">to</word>
			<word is_in_dictionary="1" ngram_probability="0.49297" percentage_of_trasnlit_rules="0.00000">kas</word>
			<word is_in_dictionary="1" ngram_probability="0.49857" percentage_of_trasnlit_rules="0.00000">atbilst</word>
			<word is_in_dictionary="1" ngram_probability="0.51016" percentage_of_trasnlit_rules="0.00000">tai</word>
			<word is_in_dictionary="1" ngram_probability="0.50301" percentage_of_trasnlit_rules="0.00000">ainai</word>
			<word is_in_dictionary="1" ngram_probability="0.50223" percentage_of_trasnlit_rules="0.00000">kas</word>
			<word is_in_dictionary="0" ngram_probability="0.00000" percentage_of_trasnlit_rules="0.00000">pašam</word>
			<word is_in_dictionary="0" ngram_probability="0.00000" percentage_of_trasnlit_rules="0.00000">galvā</word>
			<word is_in_dictionary="1" ngram_probability="0.49037" percentage_of_trasnlit_rules="0.00000">Kaut</word>
			<word is_in_dictionary="1" ngram_probability="0.49707" percentage_of_trasnlit_rules="0.00000">gaumes</word>
			<word is_in_dictionary="1" ngram_probability="0.49387" percentage_of_trasnlit_rules="0.00000">jau</word>
			<word is_in_dictionary="0" ngram_probability="0.00000" percentage_of_trasnlit_rules="0.00000">dažādas</word>
			<word is_in_dictionary="0" ngram_probability="0.00000" percentage_of_trasnlit_rules="0.00000">liberālis</word>
			<word is_in_dictionary="1" ngram_probability="0.47950" percentage_of_trasnlit_rules="0.00000">jau</word>
			<word is_in_dictionary="0" ngram_probability="0.47617" percentage_of_trasnlit_rules="0.00000">te</word>
			<word is_in_dictionary="1" ngram_probability="0.48532" percentage_of_trasnlit_rules="0.00000">daudziem</word>
			<word is_in_dictionary="1" ngram_probability="0.48482" percentage_of_trasnlit_rules="0.00000">lamu</word>
			<word is_in_dictionary="0" ngram_probability="0.00000" percentage_of_trasnlit_rules="0.00000">vārds</word>
			<word is_in_dictionary="0" ngram_probability="0.00000" percentage_of_trasnlit_rules="0.00000">īpaši</word>
			<word is_in_dictionary="1" ngram_probability="0.49406" percentage_of_trasnlit_rules="0.00000">tiem</word>
			<word is_in_dictionary="1" ngram_probability="0.50237" percentage_of_trasnlit_rules="0.00000">kam</word>
			<word is_in_dictionary="0" ngram_probability="0.00000" percentage_of_trasnlit_rules="0.00000">vispār</word>
			<word is_in_dictionary="1" ngram_probability="0.45264" percentage_of_trasnlit_rules="0.00000">nav</word>
			<word is_in_dictionary="0" ngram_probability="0.00000" percentage_of_trasnlit_rules="0.00000">nekāda</word>
			<word is_in_dictionary="0" ngram_probability="0.00000" percentage_of_trasnlit_rules="0.00000">saprašana</word>
			<word is_in_dictionary="1" ngram_probability="0.49800" percentage_of_trasnlit_rules="0.00000">ko</word>
			<word is_in_dictionary="1" ngram_probability="0.45540" percentage_of_trasnlit_rules="0.00000">tas</word>
			<word is_in_dictionary="0" ngram_probability="0.00000" percentage_of_trasnlit_rules="0.00000">vārds</word>
			<word is_in_dictionary="0" ngram_probability="0.00000" percentage_of_trasnlit_rules="0.00000">nozīmē</word>
		</words>
	</comment>
	<comment words="11" words_in_dictionary="0.54545" ngram_probability="0.27100" percentage_of_trasnlit_rules="0.00000" cumulative_probability="0.00000">
		<original>Progress? Dažreiz rodas sajūta, ka viņš vairs neatšķir rītu no vakara:)</original>
		<words>
			<word is_in_dictionary="1" ngram_probability="0.49414" percentage_of_trasnlit_rules="0.00000">Progress</word>
			<word is_in_dictionary="0" ngram_probability="0.00000" percentage_of_trasnlit_rules="0.00000">Dažreiz</word>
			<word is_in_dictionary="1" ngram_probability="0.49257" percentage_of_trasnlit_rules="0.00000">rodas</word>
			<word is_in_dictionary="0" ngram_probability="0.00000" percentage_of_trasnlit_rules="0.00000">sajūta</word>
			<word is_in_dictionary="1" ngram_probability="0.49591" percentage_of_trasnlit_rules="0.00000">ka</word>
			<word is_in_dictionary="0" ngram_probability="0.00000" percentage_of_trasnlit_rules="0.00000">viņš</word>
			<word is_in_dictionary="1" ngram_probability="0.49042" percentage_of_trasnlit_rules="0.00000">vairs</word>
			<word is_in_dictionary="0" ngram_probability="0.00000" percentage_of_trasnlit_rules="0.00000">neatšķir</word>
			<word is_in_dictionary="0" ngram_probability="0.00000" percentage_of_trasnlit_rules="0.00000">rītu</word>
			<word is_in_dictionary="1" ngram_probability="0.50312" percentage_of_trasnlit_rules="0.00000">no</word>
			<word is_in_dictionary="1" ngram_probability="0.50485" percentage_of_trasnlit_rules="0.00000">vakara</word>
		</words>
	</comment>
	<comment words="62" words_in_dictionary="0.40323" ngram_probability="0.26920" percentage_of_trasnlit_rules="0.00000" cumulative_probability="0.00000">
		<original>Kas tad būs "soģis", kas objektīvi izvērtēs katra ministra darbu? Katra partija uzskata, ka viņu ministri ir tie labākie. Domrovskim vajadzētu izvērtēt, kāpēc tiek kavētas reformas Ķīļa un Sprūdža ministrijās - tas gan tiesa. Būtu jāizvērtē - kā tas var būt, ka viens nelietīgs, ambiciozs avantūrists Olšteins var terorizēt partiju, ar kuras palīdzību iekļuvis Saeimā un kontrolē SM un gorās TV ekrānos kā varonis.</original>
		<words>
			<word is_in_dictionary="1" ngram_probability="0.50004" percentage_of_trasnlit_rules="0.00000">Kas</word>
			<word is_in_dictionary="1" ngram_probability="0.48626" percentage_of_trasnlit_rules="0.00000">tad</word>
			<word is_in_dictionary="0" ngram_probability="0.00000" percentage_of_trasnlit_rules="0.00000">būs</word>
			<word is_in_dictionary="0" ngram_probability="0.00000" percentage_of_trasnlit_rules="0.00000">soģis</word>
			<word is_in_dictionary="1" ngram_probability="0.51078" percentage_of_trasnlit_rules="0.00000">kas</word>
			<word is_in_dictionary="0" ngram_probability="0.00000" percentage_of_trasnlit_rules="0.00000">objektīvi</word>
			<word is_in_dictionary="0" ngram_probability="0.00000" percentage_of_trasnlit_rules="0.00000">izvērtēs</word>
			<word is_in_dictionary="0" ngram_probability="0.49064" percentage_of_trasnlit_rules="0.00000">katra</word>
			<word is_in_dictionary="1" ngram_probability="0.49654" percentage_of_trasnlit_rules="0.00000">ministra</word>
			<word is_in_dictionary="1" ngram_probability="0.49676" percentage_of_trasnlit_rules="0.00000">darbu</word>
			<word is_in_dictionary="0" ngram_probability="0.49334" percentage_of_trasnlit_rules="0.00000">Katra</word>
			<word is_in_dictionary="1" ngram_probability="0.49755" percentage_of_trasnlit_rules="0.00000">partija</word>
			<word is_in_dictionary="1" ngram_probability="0.49583" percentage_of_trasnlit_rules="0.00000">uzskata</word>
			<word is_in_dictionary="1" ngram_probability="0.44850" percentage_of_trasnlit_rules="0.00000">ka</word>
			<word is_in_dictionary="0" ngram_probability="0.00000" percentage_of_trasnlit_rules="0.00000">viņu</word>
			<word is_in_dictionary="0" ngram_probability="0.49705" percentage_of_trasnlit_rules="0.00000">ministri</word>
			<word is_in_dictionary="1" ngram_probability="0.47950" percentage_of_trasnlit_rules="0.00000">ir</word>
			<word is_in_dictionary="0" ngram_probability="0.49682" percentage_of_trasnlit_rules="0.00000">tie</word>
			<word is_in_dictionary="0" ngram_probability="0.00000" percentage_of_trasnlit_rules="0.00000">labākie</word>
			<word is_in_dictionary="1" ngram_probability="0.50127" percentage_of_trasnlit_rules="0.00000">Domrovskim</word>
			<word is_in_dictionary="0" ngram_probability="0.00000" percentage_of_trasnlit_rules="0.00000">vajadzētu</word>
			<word is_in_dictionary="0" ngram_probability="0.00000" percentage_of_trasnlit_rules="0.00000">izvērtēt</word>
			<word is_in_dictionary="0" ngram_probability="0.00000" percentage_of_trasnlit_rules="0.00000">kāpēc</word>
			<word is_in_dictionary="1" ngram_probability="0.47841" percentage_of_trasnlit_rules="0.00000">tiek</word>
			<word is_in_dictionary="0" ngram_probability="0.00000" percentage_of_trasnlit_rules="0.00000">kavētas</word>
			<word is_in_dictionary="1" ngram_probability="0.49537" percentage_of_trasnlit_rules="0.00000">reformas</word>
			<word is_in_dictionary="0" ngram_probability="0.00000" percentage_of_trasnlit_rules="0.00000">Ķīļa</word>
			<word is_in_dictionary="1" ngram_probability="0.43510" percentage_of_trasnlit_rules="0.00000">un</word>
			<word is_in_dictionary="0" ngram_probability="0.00000" percentage_of_trasnlit_rules="0.00000">Sprūdža</word>
			<word is_in_dictionary="0" ngram_probability="0.00000" percentage_of_trasnlit_rules="0.00000">ministrijās</word>
			<word is_in_dictionary="1" ngram_probability="0.48935" percentage_of_trasnlit_rules="0.00000">tas</word>
			<word is_in_dictionary="1" ngram_probability="0.48307" percentage_of_trasnlit_rules="0.00000">gan</word>
			<word is_in_dictionary="0" ngram_probability="0.49529" percentage_of_trasnlit_rules="0.00000">tiesa</word>
			<word is_in_dictionary="0" ngram_probability="0.00000" percentage_of_trasnlit_rules="0.00000">Būtu</word>
			<word is_in_dictionary="0" ngram_probability="0.00000" percentage_of_trasnlit_rules="0.00000">jāizvērtē</word>
			<word is_in_dictionary="0" ngram_probability="0.00000" percentage_of_trasnlit_rules="0.00000">kā</word>
			<word is_in_dictionary="1" ngram_probability="0.49432" percentage_of_trasnlit_rules="0.00000">tas</word>
			<word is_in_dictionary="0" ngram_probability="0.48774" percentage_of_trasnlit_rules="0.00000">var</word>
			<word is_in_dictionary="0" ngram_probability="0.00000" percentage_of_trasnlit_rules="0.00000">būt</word>
			<word is_in_dictionary="1" ngram_probability="0.49963" percentage_of_trasnlit_rules="0.00000">ka</word>
			<word is_in_dictionary="1" ngram_probability="0.49197" percentage_of_trasnlit_rules="0.00000">viens</word>
			<word is_in_dictionary="0" ngram_probability="0.00000" percentage_of_trasnlit_rules="0.00000">nelietīgs</word>
			<word is_in_dictionary="1" ngram_probability="0.48559" percentage_of_trasnlit_rules="0.00000">ambiciozs</word>
			<word is_in_dictionary="0" ngram_probability="0.00000" percentage_of_trasnlit_rules="0.00000">avantūrists</word>
			<word is_in_dictionary="0" ngram_probability="0.00000" percentage_of_trasnlit_rules="0.00000">Olšteins</word>
			<word is_in_dictionary="0" ngram_probability="0.50513" percentage_of_trasnlit_rules="0.00000">var</word>
			<word is_in_dictionary="0" ngram_probability="0.00000" percentage_of_trasnlit_rules="0.00000">terorizēt</word>
			<word is_in_dictionary="1" ngram_probability="0.50127" percentage_of_trasnlit_rules="0.00000">partiju</word>
			<word is_in_dictionary="1" ngram_probability="0.45264" percentage_of_trasnlit_rules="0.00000">ar</word>
			<word is_in_dictionary="1" ngram_probability="0.48660" percentage_of_trasnlit_rules="0.00000">kuras</word>
			<word is_in_dictionary="0" ngram_probability="0.00000" percentage_of_trasnlit_rules="0.00000">palīdzību</word>
			<word is_in_dictionary="0" ngram_probability="0.00000" percentage_of_trasnlit_rules="0.00000">iekļuvis</word>
			<word is_in_dictionary="0" ngram_probability="0.00000" percentage_of_trasnlit_rules="0.00000">Saeimā</word>
			<word is_in_dictionary="1" ngram_probability="0.49063" percentage_of_trasnlit_rules="0.00000">un</word>
			<word is_in_dictionary="0" ngram_probability="0.00000" percentage_of_trasnlit_rules="0.00000">kontrolē</word>
			<word is_in_dictionary="0" ngram_probability="0.49297" percentage_of_trasnlit_rules="0.00000">SM</word>
			<word is_in_dictionary="1" ngram_probability="0.48450" percentage_of_trasnlit_rules="0.00000">un</word>
			<word is_in_dictionary="0" ngram_probability="0.00000" percentage_of_trasnlit_rules="0.00000">gorās</word>
			<word is_in_dictionary="0" ngram_probability="0.49429" percentage_of_trasnlit_rules="0.00000">TV</word>
			<word is_in_dictionary="0" ngram_probability="0.00000" percentage_of_trasnlit_rules="0.00000">ekrānos</word>
			<word is_in_dictionary="0" ngram_probability="0.00000" percentage_of_trasnlit_rules="0.00000">kā</word>
			<word is_in_dictionary="1" ngram_probability="0.55584" percentage_of_trasnlit_rules="0.00000">varonis</word>
		</words>
	</comment>
	<comment words="32" words_in_dictionary="0.56250" ngram_probability="0.31256" percentage_of_trasnlit_rules="0.00000" cumulative_probability="0.00000">
		<original>Viņš jau to būs jau atdevis un Zatlers sen iztērējis. Tāpēc nekādi nevar saprast, ka RP jau sen marginalizējusies. Un tāpec citi, tapat kā pārejos margināļus (Daugavas racējus u.c.)vairs neņem par pilnu.</original>
		<words>
			<word is_in_dictionary="0" ngram_probability="0.00000" percentage_of_trasnlit_rules="0.00000">Viņš</word>
			<word is_in_dictionary="1" ngram_probability="0.48704" percentage_of_trasnlit_rules="0.00000">jau</word>
			<word is_in_dictionary="1" ngram_probability="0.49037" percentage_of_trasnlit_rules="0.00000">to</word>
			<word is_in_dictionary="0" ngram_probability="0.00000" percentage_of_trasnlit_rules="0.00000">būs</word>
			<word is_in_dictionary="1" ngram_probability="0.49271" percentage_of_trasnlit_rules="0.00000">jau</word>
			<word is_in_dictionary="1" ngram_probability="0.55889" percentage_of_trasnlit_rules="0.00000">atdevis</word>
			<word is_in_dictionary="1" ngram_probability="0.43510" percentage_of_trasnlit_rules="0.00000">un</word>
			<word is_in_dictionary="1" ngram_probability="0.47738" percentage_of_trasnlit_rules="0.00000">Zatlers</word>
			<word is_in_dictionary="1" ngram_probability="0.48836" percentage_of_trasnlit_rules="0.00000">sen</word>
			<word is_in_dictionary="0" ngram_probability="0.00000" percentage_of_trasnlit_rules="0.00000">iztērējis</word>
			<word is_in_dictionary="0" ngram_probability="0.00000" percentage_of_trasnlit_rules="0.00000">Tāpēc</word>
			<word is_in_dictionary="0" ngram_probability="0.00000" percentage_of_trasnlit_rules="0.00000">nekādi</word>
			<word is_in_dictionary="1" ngram_probability="0.48889" percentage_of_trasnlit_rules="0.00000">nevar</word>
			<word is_in_dictionary="1" ngram_probability="0.47752" percentage_of_trasnlit_rules="0.00000">saprast</word>
			<word is_in_dictionary="1" ngram_probability="0.50228" percentage_of_trasnlit_rules="0.00000">ka</word>
			<word is_in_dictionary="0" ngram_probability="0.49783" percentage_of_trasnlit_rules="0.00000">RP</word>
			<word is_in_dictionary="1" ngram_probability="0.54173" percentage_of_trasnlit_rules="0.00000">jau</word>
			<word is_in_dictionary="1" ngram_probability="0.49488" percentage_of_trasnlit_rules="0.00000">sen</word>
			<word is_in_dictionary="0" ngram_probability="0.00000" percentage_of_trasnlit_rules="0.00000">marginalizējusies</word>
			<word is_in_dictionary="1" ngram_probability="0.48837" percentage_of_trasnlit_rules="0.00000">Un</word>
			<word is_in_dictionary="0" ngram_probability="0.00000" percentage_of_trasnlit_rules="0.00000">tāpec</word>
			<word is_in_dictionary="0" ngram_probability="0.48866" percentage_of_trasnlit_rules="0.00000">citi</word>
			<word is_in_dictionary="1" ngram_probability="0.51202" percentage_of_trasnlit_rules="0.00000">tapat</word>
			<word is_in_dictionary="0" ngram_probability="0.00000" percentage_of_trasnlit_rules="0.00000">kā</word>
			<word is_in_dictionary="0" ngram_probability="0.00000" percentage_of_trasnlit_rules="0.00000">pārejos</word>
			<word is_in_dictionary="0" ngram_probability="0.00000" percentage_of_trasnlit_rules="0.00000">margināļus</word>
			<word is_in_dictionary="1" ngram_probability="0.49831" percentage_of_trasnlit_rules="0.00000">Daugavas</word>
			<word is_in_dictionary="0" ngram_probability="0.00000" percentage_of_trasnlit_rules="0.00000">racējus</word>
			<word is_in_dictionary="1" ngram_probability="0.59415" percentage_of_trasnlit_rules="0.00000">vairs</word>
			<word is_in_dictionary="0" ngram_probability="0.00000" percentage_of_trasnlit_rules="0.00000">neņem</word>
			<word is_in_dictionary="1" ngram_probability="0.49069" percentage_of_trasnlit_rules="0.00000">par</word>
			<word is_in_dictionary="1" ngram_probability="0.49677" percentage_of_trasnlit_rules="0.00000">pilnu</word>
		</words>
	</comment>
	<comment words="33" words_in_dictionary="0.48485" ngram_probability="0.26844" percentage_of_trasnlit_rules="0.00000" cumulative_probability="0.00000">
		<original>Kopējais bērnu skaits, kuri 2012./2013. mācību gadā nav reģistrēti nevienas izglītības iestādes sarakstā, ir 12 618, bet 2011.gadā tādu bija 12 463, savukārt 2010.gadā kopējais bērnu skaits bija 11 327.</original>
		<words>
			<word is_in_dictionary="0" ngram_probability="0.00000" percentage_of_trasnlit_rules="0.00000">Kopējais</word>
			<word is_in_dictionary="0" ngram_probability="0.00000" percentage_of_trasnlit_rules="0.00000">bērnu</word>
			<word is_in_dictionary="1" ngram_probability="0.49124" percentage_of_trasnlit_rules="0.00000">skaits</word>
			<word is_in_dictionary="1" ngram_probability="0.52020" percentage_of_trasnlit_rules="0.00000">kuri</word>
			<word is_in_dictionary="1" ngram_probability="0.23766" percentage_of_trasnlit_rules="0.00000">2012</word>
			<word is_in_dictionary="1" ngram_probability="0.23783" percentage_of_trasnlit_rules="0.00000">2013</word>
			<word is_in_dictionary="0" ngram_probability="0.00000" percentage_of_trasnlit_rules="0.00000">mācību</word>
			<word is_in_dictionary="0" ngram_probability="0.00000" percentage_of_trasnlit_rules="0.00000">gadā</word>
			<word is_in_dictionary="1" ngram_probability="0.45264" percentage_of_trasnlit_rules="0.00000">nav</word>
			<word is_in_dictionary="0" ngram_probability="0.00000" percentage_of_trasnlit_rules="0.00000">reģistrēti</word>
			<word is_in_dictionary="1" ngram_probability="0.49721" percentage_of_trasnlit_rules="0.00000">nevienas</word>
			<word is_in_dictionary="0" ngram_probability="0.00000" percentage_of_trasnlit_rules="0.00000">izglītības</word>
			<word is_in_dictionary="0" ngram_probability="0.00000" percentage_of_trasnlit_rules="0.00000">iestādes</word>
			<word is_in_dictionary="0" ngram_probability="0.00000" percentage_of_trasnlit_rules="0.00000">sarakstā</word>
			<word is_in_dictionary="1" ngram_probability="0.49841" percentage_of_trasnlit_rules="0.00000">ir</word>
			<word is_in_dictionary="0" ngram_probability="0.59914" percentage_of_trasnlit_rules="0.00000">12</word>
			<word is_in_dictionary="1" ngram_probability="0.48325" percentage_of_trasnlit_rules="0.00000">618</word>
			<word is_in_dictionary="1" ngram_probability="0.47939" percentage_of_trasnlit_rules="0.00000">bet</word>
			<word is_in_dictionary="1" ngram_probability="0.49354" percentage_of_trasnlit_rules="0.00000">2011</word>
			<word is_in_dictionary="0" ngram_probability="0.00000" percentage_of_trasnlit_rules="0.00000">gadā</word>
			<word is_in_dictionary="0" ngram_probability="0.00000" percentage_of_trasnlit_rules="0.00000">tādu</word>
			<word is_in_dictionary="1" ngram_probability="0.51008" percentage_of_trasnlit_rules="0.00000">bija</word>
			<word is_in_dictionary="0" ngram_probability="0.45386" percentage_of_trasnlit_rules="0.00000">12</word>
			<word is_in_dictionary="1" ngram_probability="0.43510" percentage_of_trasnlit_rules="0.00000">463</word>
			<word is_in_dictionary="0" ngram_probability="0.00000" percentage_of_trasnlit_rules="0.00000">savukārt</word>
			<word is_in_dictionary="1" ngram_probability="0.57516" percentage_of_trasnlit_rules="0.00000">2010</word>
			<word is_in_dictionary="0" ngram_probability="0.00000" percentage_of_trasnlit_rules="0.00000">gadā</word>
			<word is_in_dictionary="0" ngram_probability="0.00000" percentage_of_trasnlit_rules="0.00000">kopējais</word>
			<word is_in_dictionary="0" ngram_probability="0.00000" percentage_of_trasnlit_rules="0.00000">bērnu</word>
			<word is_in_dictionary="1" ngram_probability="0.47907" percentage_of_trasnlit_rules="0.00000">skaits</word>
			<word is_in_dictionary="1" ngram_probability="0.44850" percentage_of_trasnlit_rules="0.00000">bija</word>
			<word is_in_dictionary="0" ngram_probability="0.48112" percentage_of_trasnlit_rules="0.00000">11</word>
			<word is_in_dictionary="1" ngram_probability="0.48525" percentage_of_trasnlit_rules="0.00000">327</word>
		</words>
	</comment>
	<comment words="25" words_in_dictionary="0.36000" ngram_probability="0.21521" percentage_of_trasnlit_rules="0.00000" cumulative_probability="0.00000">
		<original>Kvalitātes dienestam, balstoties uz šo informāciju un sekojot pašvaldību rīcībai, turpmāk būs lielākas iespējas sniegt nepieciešamo atbalstu un konsultācijas, lai tiktu nodrošināta obligātās izglītības ieguve.</original>
		<words>
			<word is_in_dictionary="0" ngram_probability="0.00000" percentage_of_trasnlit_rules="0.00000">Kvalitātes</word>
			<word is_in_dictionary="1" ngram_probability="0.50167" percentage_of_trasnlit_rules="0.00000">dienestam</word>
			<word is_in_dictionary="1" ngram_probability="0.49423" percentage_of_trasnlit_rules="0.00000">balstoties</word>
			<word is_in_dictionary="1" ngram_probability="0.51203" percentage_of_trasnlit_rules="0.00000">uz</word>
			<word is_in_dictionary="0" ngram_probability="0.00000" percentage_of_trasnlit_rules="0.00000">šo</word>
			<word is_in_dictionary="0" ngram_probability="0.00000" percentage_of_trasnlit_rules="0.00000">informāciju</word>
			<word is_in_dictionary="1" ngram_probability="0.48367" percentage_of_trasnlit_rules="0.00000">un</word>
			<word is_in_dictionary="1" ngram_probability="0.43510" percentage_of_trasnlit_rules="0.00000">sekojot</word>
			<word is_in_dictionary="0" ngram_probability="0.00000" percentage_of_trasnlit_rules="0.00000">pašvaldību</word>
			<word is_in_dictionary="0" ngram_probability="0.00000" percentage_of_trasnlit_rules="0.00000">rīcībai</word>
			<word is_in_dictionary="0" ngram_probability="0.00000" percentage_of_trasnlit_rules="0.00000">turpmāk</word>
			<word is_in_dictionary="0" ngram_probability="0.00000" percentage_of_trasnlit_rules="0.00000">būs</word>
			<word is_in_dictionary="0" ngram_probability="0.00000" percentage_of_trasnlit_rules="0.00000">lielākas</word>
			<word is_in_dictionary="0" ngram_probability="0.00000" percentage_of_trasnlit_rules="0.00000">iespējas</word>
			<word is_in_dictionary="0" ngram_probability="0.48625" percentage_of_trasnlit_rules="0.00000">sniegt</word>
			<word is_in_dictionary="0" ngram_probability="0.00000" percentage_of_trasnlit_rules="0.00000">nepieciešamo</word>
			<word is_in_dictionary="1" ngram_probability="0.49424" percentage_of_trasnlit_rules="0.00000">atbalstu</word>
			<word is_in_dictionary="1" ngram_probability="0.48113" percentage_of_trasnlit_rules="0.00000">un</word>
			<word is_in_dictionary="0" ngram_probability="0.00000" percentage_of_trasnlit_rules="0.00000">konsultācijas</word>
			<word is_in_dictionary="1" ngram_probability="0.50375" percentage_of_trasnlit_rules="0.00000">lai</word>
			<word is_in_dictionary="1" ngram_probability="0.50016" percentage_of_trasnlit_rules="0.00000">tiktu</word>
			<word is_in_dictionary="0" ngram_probability="0.00000" percentage_of_trasnlit_rules="0.00000">nodrošināta</word>
			<word is_in_dictionary="0" ngram_probability="0.00000" percentage_of_trasnlit_rules="0.00000">obligātās</word>
			<word is_in_dictionary="0" ngram_probability="0.00000" percentage_of_trasnlit_rules="0.00000">izglītības</word>
			<word is_in_dictionary="0" ngram_probability="0.48804" percentage_of_trasnlit_rules="0.00000">ieguve</word>
		</words>
	</comment>
	<comment words="23" words_in_dictionary="0.47826" ngram_probability="0.25056" percentage_of_trasnlit_rules="0.00000" cumulative_probability="0.00000">
		<original>Pieaugums, iespējams % attiecībā pret kopējo bērnu skaitu. Es gan uzskatu, ka grāmatvediska manipulācija vairāk VID, nodokļu iekasēšanai. Ar dzīves kvalitāti tai pamazs sakars.</original>
		<words>
			<word is_in_dictionary="1" ngram_probability="0.50470" percentage_of_trasnlit_rules="0.00000">Pieaugums</word>
			<word is_in_dictionary="0" ngram_probability="0.00000" percentage_of_trasnlit_rules="0.00000">iespējams</word>
			<word is_in_dictionary="0" ngram_probability="0.00000" percentage_of_trasnlit_rules="0.00000">attiecībā</word>
			<word is_in_dictionary="1" ngram_probability="0.46696" percentage_of_trasnlit_rules="0.00000">pret</word>
			<word is_in_dictionary="0" ngram_probability="0.00000" percentage_of_trasnlit_rules="0.00000">kopējo</word>
			<word is_in_dictionary="0" ngram_probability="0.00000" percentage_of_trasnlit_rules="0.00000">bērnu</word>
			<word is_in_dictionary="1" ngram_probability="0.44850" percentage_of_trasnlit_rules="0.00000">skaitu</word>
			<word is_in_dictionary="1" ngram_probability="0.48107" percentage_of_trasnlit_rules="0.00000">Es</word>
			<word is_in_dictionary="1" ngram_probability="0.49812" percentage_of_trasnlit_rules="0.00000">gan</word>
			<word is_in_dictionary="1" ngram_probability="0.50140" percentage_of_trasnlit_rules="0.00000">uzskatu</word>
			<word is_in_dictionary="1" ngram_probability="0.48737" percentage_of_trasnlit_rules="0.00000">ka</word>
			<word is_in_dictionary="0" ngram_probability="0.00000" percentage_of_trasnlit_rules="0.00000">grāmatvediska</word>
			<word is_in_dictionary="0" ngram_probability="0.00000" percentage_of_trasnlit_rules="0.00000">manipulācija</word>
			<word is_in_dictionary="0" ngram_probability="0.00000" percentage_of_trasnlit_rules="0.00000">vairāk</word>
			<word is_in_dictionary="0" ngram_probability="0.44850" percentage_of_trasnlit_rules="0.00000">VID</word>
			<word is_in_dictionary="0" ngram_probability="0.00000" percentage_of_trasnlit_rules="0.00000">nodokļu</word>
			<word is_in_dictionary="0" ngram_probability="0.00000" percentage_of_trasnlit_rules="0.00000">iekasēšanai</word>
			<word is_in_dictionary="1" ngram_probability="0.49196" percentage_of_trasnlit_rules="0.00000">Ar</word>
			<word is_in_dictionary="0" ngram_probability="0.00000" percentage_of_trasnlit_rules="0.00000">dzīves</word>
			<word is_in_dictionary="0" ngram_probability="0.00000" percentage_of_trasnlit_rules="0.00000">kvalitāti</word>
			<word is_in_dictionary="1" ngram_probability="0.48912" percentage_of_trasnlit_rules="0.00000">tai</word>
			<word is_in_dictionary="1" ngram_probability="0.46696" percentage_of_trasnlit_rules="0.00000">pamazs</word>
			<word is_in_dictionary="1" ngram_probability="0.47832" percentage_of_trasnlit_rules="0.00000">sakars</word>
		</words>
	</comment>
	<comment words="25" words_in_dictionary="0.44000" ngram_probability="0.21827" percentage_of_trasnlit_rules="0.00000" cumulative_probability="0.00000">
		<original>Stabilitāte Eiropā bija būtiskākā paneļa „Eiropas konteksts" tēma. Tā dalībnieki apsprieda, kāds varētu būt Eiropas nākotnes modelis, un diskutēja par pārmaiņām, kas skar Eiropas reģionu.</original>
		<words>
			<word is_in_dictionary="0" ngram_probability="0.00000" percentage_of_trasnlit_rules="0.00000">Stabilitāte</word>
			<word is_in_dictionary="0" ngram_probability="0.00000" percentage_of_trasnlit_rules="0.00000">Eiropā</word>
			<word is_in_dictionary="1" ngram_probability="0.52420" percentage_of_trasnlit_rules="0.00000">bija</word>
			<word is_in_dictionary="0" ngram_probability="0.00000" percentage_of_trasnlit_rules="0.00000">būtiskākā</word>
			<word is_in_dictionary="0" ngram_probability="0.00000" percentage_of_trasnlit_rules="0.00000">paneļa</word>
			<word is_in_dictionary="1" ngram_probability="0.48831" percentage_of_trasnlit_rules="0.00000">Eiropas</word>
			<word is_in_dictionary="1" ngram_probability="0.49432" percentage_of_trasnlit_rules="0.00000">konteksts</word>
			<word is_in_dictionary="0" ngram_probability="0.00000" percentage_of_trasnlit_rules="0.00000">tēma</word>
			<word is_in_dictionary="0" ngram_probability="0.00000" percentage_of_trasnlit_rules="0.00000">Tā</word>
			<word is_in_dictionary="0" ngram_probability="0.00000" percentage_of_trasnlit_rules="0.00000">dalībnieki</word>
			<word is_in_dictionary="1" ngram_probability="0.49295" percentage_of_trasnlit_rules="0.00000">apsprieda</word>
			<word is_in_dictionary="0" ngram_probability="0.00000" percentage_of_trasnlit_rules="0.00000">kāds</word>
			<word is_in_dictionary="0" ngram_probability="0.00000" percentage_of_trasnlit_rules="0.00000">varētu</word>
			<word is_in_dictionary="0" ngram_probability="0.00000" percentage_of_trasnlit_rules="0.00000">būt</word>
			<word is_in_dictionary="1" ngram_probability="0.48654" percentage_of_trasnlit_rules="0.00000">Eiropas</word>
			<word is_in_dictionary="0" ngram_probability="0.00000" percentage_of_trasnlit_rules="0.00000">nākotnes</word>
			<word is_in_dictionary="1" ngram_probability="0.48345" percentage_of_trasnlit_rules="0.00000">modelis</word>
			<word is_in_dictionary="1" ngram_probability="0.50228" percentage_of_trasnlit_rules="0.00000">un</word>
			<word is_in_dictionary="0" ngram_probability="0.00000" percentage_of_trasnlit_rules="0.00000">diskutēja</word>
			<word is_in_dictionary="1" ngram_probability="0.48574" percentage_of_trasnlit_rules="0.00000">par</word>
			<word is_in_dictionary="0" ngram_probability="0.00000" percentage_of_trasnlit_rules="0.00000">pārmaiņām</word>
			<word is_in_dictionary="1" ngram_probability="0.48654" percentage_of_trasnlit_rules="0.00000">kas</word>
			<word is_in_dictionary="1" ngram_probability="0.50623" percentage_of_trasnlit_rules="0.00000">skar</word>
			<word is_in_dictionary="1" ngram_probability="0.50622" percentage_of_trasnlit_rules="0.00000">Eiropas</word>
			<word is_in_dictionary="0" ngram_probability="0.00000" percentage_of_trasnlit_rules="0.00000">reģionu</word>
		</words>
	</comment>
	<comment words="29" words_in_dictionary="0.34483" ngram_probability="0.18383" percentage_of_trasnlit_rules="0.00000" cumulative_probability="0.00000">
		<original>Un jābeidz vienreiz gausties par 200000 aibraukušo. Vairums atgriezīsies tāpat kā Īrijā, bet būs kļuvuši gudrāki, drosmīgāki, bagātāki. Viņi jau tagad neaizmirst palikušos, bet dalās, ceļot vispārējo labklājību Latvijā.</original>
		<words>
			<word is_in_dictionary="1" ngram_probability="0.46169" percentage_of_trasnlit_rules="0.00000">Un</word>
			<word is_in_dictionary="0" ngram_probability="0.00000" percentage_of_trasnlit_rules="0.00000">jābeidz</word>
			<word is_in_dictionary="1" ngram_probability="0.49829" percentage_of_trasnlit_rules="0.00000">vienreiz</word>
			<word is_in_dictionary="1" ngram_probability="0.48137" percentage_of_trasnlit_rules="0.00000">gausties</word>
			<word is_in_dictionary="1" ngram_probability="0.48525" percentage_of_trasnlit_rules="0.00000">par</word>
			<word is_in_dictionary="1" ngram_probability="0.49783" percentage_of_trasnlit_rules="0.00000">200000</word>
			<word is_in_dictionary="0" ngram_probability="0.00000" percentage_of_trasnlit_rules="0.00000">aibraukušo</word>
			<word is_in_dictionary="1" ngram_probability="0.50379" percentage_of_trasnlit_rules="0.00000">Vairums</word>
			<word is_in_dictionary="0" ngram_probability="0.00000" percentage_of_trasnlit_rules="0.00000">atgriezīsies</word>
			<word is_in_dictionary="0" ngram_probability="0.00000" percentage_of_trasnlit_rules="0.00000">tāpat</word>
			<word is_in_dictionary="0" ngram_probability="0.00000" percentage_of_trasnlit_rules="0.00000">kā</word>
			<word is_in_dictionary="0" ngram_probability="0.00000" percentage_of_trasnlit_rules="0.00000">Īrijā</word>
			<word is_in_dictionary="1" ngram_probability="0.47640" percentage_of_trasnlit_rules="0.00000">bet</word>
			<word is_in_dictionary="0" ngram_probability="0.00000" percentage_of_trasnlit_rules="0.00000">būs</word>
			<word is_in_dictionary="0" ngram_probability="0.00000" percentage_of_trasnlit_rules="0.00000">kļuvuši</word>
			<word is_in_dictionary="0" ngram_probability="0.00000" percentage_of_trasnlit_rules="0.00000">gudrāki</word>
			<word is_in_dictionary="0" ngram_probability="0.00000" percentage_of_trasnlit_rules="0.00000">drosmīgāki</word>
			<word is_in_dictionary="0" ngram_probability="0.00000" percentage_of_trasnlit_rules="0.00000">bagātāki</word>
			<word is_in_dictionary="0" ngram_probability="0.00000" percentage_of_trasnlit_rules="0.00000">Viņi</word>
			<word is_in_dictionary="1" ngram_probability="0.51719" percentage_of_trasnlit_rules="0.00000">jau</word>
			<word is_in_dictionary="1" ngram_probability="0.49873" percentage_of_trasnlit_rules="0.00000">tagad</word>
			<word is_in_dictionary="0" ngram_probability="0.47556" percentage_of_trasnlit_rules="0.00000">neaizmirst</word>
			<word is_in_dictionary="0" ngram_probability="0.00000" percentage_of_trasnlit_rules="0.00000">palikušos</word>
			<word is_in_dictionary="1" ngram_probability="0.43510" percentage_of_trasnlit_rules="0.00000">bet</word>
			<word is_in_dictionary="0" ngram_probability="0.00000" percentage_of_trasnlit_rules="0.00000">dalās</word>
			<word is_in_dictionary="0" ngram_probability="0.00000" percentage_of_trasnlit_rules="0.00000">ceļot</word>
			<word is_in_dictionary="0" ngram_probability="0.00000" percentage_of_trasnlit_rules="0.00000">vispārējo</word>
			<word is_in_dictionary="0" ngram_probability="0.00000" percentage_of_trasnlit_rules="0.00000">labklājību</word>
			<word is_in_dictionary="0" ngram_probability="0.00000" percentage_of_trasnlit_rules="0.00000">Latvijā</word>
		</words>
	</comment>
</comments>
